django_rds_iam_auth/__init__.py
django_rds_iam_auth/authentication.py
django_rds_iam_auth/exceptions.py
django_rds_iam_auth/models.py
django_rds_iam_auth/utils.py
django_rds_iam_auth/aws/__init__.py
django_rds_iam_auth/aws/postgresql/__init__.py
django_rds_iam_auth/aws/postgresql/base.py
django_rds_iam_auth/aws/postgresql/model_helpers.py
django_rds_iam_auth/aws/utils/__init__.py
django_rds_iam_auth/aws/utils/aws_access_heper.py
django_rds_iam_auth/aws/utils/rls_helpers.py
django_rds_iam_auth/aws/utils/user_data_heper.py
django_rds_iam_auth/management/__init__.py
django_rds_iam_auth/management/commands/__init__.py
django_rds_iam_auth/management/commands/generate_rls_migrations.py
django_rds_iam_auth/middleware/__init__.py
django_rds_iam_auth/middleware/check_tenant_status.py
django_rds_iam_auth/middleware/check_user_status.py
django_rds_iam_auth/middleware/db_routers.py
django_rds_iam_auth/middleware/dynamic_conn_injector.py
django_rds_iam_auth/middleware/jwt_exposer.py
django_rds_iam_auth/middleware/jwt_injector.py
django_rds_iam_auth/middleware/redirect_on_event.py
django_rds_iam_auth/middleware/rls_backend.py
django_rds_iam_auth/middleware/token_custom_cookie_injector.py
django_rds_iam_auth/middleware/user_injector.py
django_rds_iam_auth/middleware/verify_token.py
django_rds_iam_auth/migrations/0001_initial.py
django_rds_iam_auth/migrations/0007_auto_20200425_1815.py
django_rds_iam_auth/migrations/0008_auto_20200425_1824.py
django_rds_iam_auth/migrations/0009_auto_20200425_1824.py
django_rds_iam_auth/migrations/0010_auto_20200425_1824.py
django_rds_iam_auth/migrations/0011_auto_20200425_1824.py
django_rds_iam_auth/migrations/0012_auto_20200425_1824.py
django_rds_iam_auth/migrations/0013_auto_20200425_1824.py
django_rds_iam_auth/migrations/0014_auto_20200425_1824.py
django_rds_iam_auth/migrations/0015_auto_20200425_1825.py
django_rds_iam_auth/migrations/0016_auto_20200429_1809.py
django_rds_iam_auth/migrations/0018_auto_20200502_1117.py
django_rds_iam_auth-0.0.88.dist-info/LICENSE
django_rds_iam_auth-0.0.88.dist-info/METADATA
django_rds_iam_auth-0.0.88.dist-info/WHEEL
django_rds_iam_auth-0.0.88.dist-info/top_level.txt
django_rds_iam_auth-0.0.88.dist-info/RECORD
